motndp/__init__.py
motndp/city.py
motndp/constraints.py
motndp/motndp.py
motndp-0.1.0.dist-info/LICENSE
motndp-0.1.0.dist-info/METADATA
motndp-0.1.0.dist-info/WHEEL
motndp-0.1.0.dist-info/top_level.txt
motndp-0.1.0.dist-info/RECORD
