Metadata-Version: 2.1
Name: motndp
Version: 0.1.0
Summary: Multi-Objective Transport Network Design Problem gymnasium environment.
Author-email: Dimitris Michailidis <dimichai@outlook.com>
License: MIT License
Project-URL: Repository, https://github.com/dimichai/mo-tndp
Keywords: Reinforcement Learning,Multi-Objective,RL,AI,Tranportation Network
Classifier: Development Status :: 4 - Beta
Classifier: Intended Audience :: Science/Research
Classifier: License :: OSI Approved :: MIT License
Classifier: Programming Language :: Python :: 3
Classifier: Programming Language :: Python :: 3.8
Classifier: Programming Language :: Python :: 3.9
Classifier: Programming Language :: Python :: 3.10
Classifier: Programming Language :: Python :: 3.11
Classifier: Programming Language :: Python :: 3.12
Classifier: Topic :: Scientific/Engineering :: Artificial Intelligence
Requires-Python: >=3.8
License-File: LICENSE
Requires-Dist: gymnasium >=1.0.0
Requires-Dist: numpy <2.0,>=1.21.0
Requires-Dist: pygame >=2.1.3
